tests/__init__.py
tests/test_dashboard.py
tests/test_example.py
tests/test_forms.py
tests/test_manager.py
tests/test_multipoll_example.py
tests/test_results.py
tests/test_tools.py
vxpolls/__init__.py
vxpolls/dashboard.py
vxpolls/example.py
vxpolls/manage.py
vxpolls/manager.py
vxpolls/multipoll_example.py
vxpolls/participant.py
vxpolls/results.py
vxpolls/settings.py
vxpolls/urls.py
vxpolls/content/__init__.py
vxpolls/content/fields.py
vxpolls/content/forms.py
vxpolls/content/models.py
vxpolls/content/tests.py
vxpolls/content/urls.py
vxpolls/content/views.py
vxpolls/djdashboard/__init__.py
vxpolls/djdashboard/models.py
vxpolls/djdashboard/tests.py
vxpolls/djdashboard/urls.py
vxpolls/djdashboard/views.py
vxpolls/tools/__init__.py
vxpolls/tools/exporter.py
vxpolls/tools/importer.py
vxpolls-0.1.0.dist-info/DESCRIPTION.rst
vxpolls-0.1.0.dist-info/METADATA
vxpolls-0.1.0.dist-info/metadata.json
vxpolls-0.1.0.dist-info/RECORD
vxpolls-0.1.0.dist-info/top_level.txt
vxpolls-0.1.0.dist-info/WHEEL
