Metadata-Version: 2.0
Name: vxpolls
Version: 0.1.0
Summary: Simple polling / survey framework for Vumi apps
Home-page: http://github.com/praekelt/vxpolls
Author: Praekelt Foundation
Author-email: dev@praekeltfoundation.org
License: BSD
Platform: UNKNOWN
Classifier: Development Status :: 7 - Inactive
Classifier: Intended Audience :: Developers
Classifier: License :: OSI Approved :: BSD License
Classifier: Operating System :: POSIX
Classifier: Programming Language :: Python
Classifier: Topic :: Software Development :: Libraries :: Python Modules
Requires-Dist: vumi
